xhs_mcp_cli/__about__.py
xhs_mcp_cli/__init__.py
xhs_mcp_cli/app.py
xhs_mcp_cli/api/xhs_api.py
xhs_mcp_cli/api/xhsvm.js
xhs_mcp_cli-0.1.1.dist-info/METADATA
xhs_mcp_cli-0.1.1.dist-info/WHEEL
xhs_mcp_cli-0.1.1.dist-info/entry_points.txt
xhs_mcp_cli-0.1.1.dist-info/licenses/LICENSE
xhs_mcp_cli-0.1.1.dist-info/RECORD
